dashai_gemma_model_package/__init__.py
dashai_gemma_model_package/gemma_model.py
dashai_gemma_model_package-0.0.1.dist-info/METADATA
dashai_gemma_model_package-0.0.1.dist-info/WHEEL
dashai_gemma_model_package-0.0.1.dist-info/entry_points.txt
dashai_gemma_model_package-0.0.1.dist-info/RECORD
